foolnet/__init__.py
foolnet/dataset/__init__.py
foolnet/dataset/classification.py
foolnet/network/__init__.py
foolnet/network/activation/__init__.py
foolnet/network/activation/relu.py
foolnet/network/activation/sigmoid.py
foolnet/network/activation/softmax.py
foolnet/network/layers/__init__.py
foolnet/network/layers/denseLayer.py
foolnet/network/stack/__init__.py
foolnet/optim/__init__.py
foolnet/optim/lossfn/__init__.py
foolnet/optim/lossfn/crossEntropy.py
foolnet/optim/optimizer/__init__.py
foolnet/optim/scheduler/__init__.py
foolnet-0.3.2.dist-info/LICENSE
foolnet-0.3.2.dist-info/METADATA
foolnet-0.3.2.dist-info/WHEEL
foolnet-0.3.2.dist-info/RECORD
