Metadata-Version: 2.1
Name: foolnet
Version: 0.3.2
Summary: A package designed for the newer about the Neural Network.
License: MIT
Author: lazypool
Author-email: 3416382833@qq.com
Requires-Python: >=3.9
Classifier: License :: OSI Approved :: MIT License
Classifier: Programming Language :: Python :: 3
Classifier: Programming Language :: Python :: 3.9
Classifier: Programming Language :: Python :: 3.10
Classifier: Programming Language :: Python :: 3.11
Classifier: Programming Language :: Python :: 3.12
Requires-Dist: matplotlib (>=3.8.0)
Requires-Dist: numpy (>=1.20.0)
